codetective/__init__.py
codetective/__main__.py
codetective/agents/__init__.py
codetective/agents/ai_base.py
codetective/agents/base.py
codetective/agents/output/__init__.py
codetective/agents/output/comment_agent.py
codetective/agents/output/edit_agent.py
codetective/agents/scan/__init__.py
codetective/agents/scan/dynamic_ai_review_agent.py
codetective/agents/scan/semgrep_agent.py
codetective/agents/scan/trivy_agent.py
codetective/cli/__init__.py
codetective/cli/commands.py
codetective/core/__init__.py
codetective/core/config.py
codetective/core/orchestrator.py
codetective/core/search.py
codetective/gui/__init__.py
codetective/gui/nicegui_app.py
codetective/models/__init__.py
codetective/models/schemas.py
codetective/security/__init__.py
codetective/security/input_validator.py
codetective/security/output_filter.py
codetective/security/prompt_guard.py
codetective/utils/__init__.py
codetective/utils/file_utils.py
codetective/utils/git_utils.py
codetective/utils/process_utils.py
codetective/utils/prompt_builder.py
codetective/utils/string_utils.py
codetective/utils/system_utils.py
codetective-0.1.0.dist-info/licenses/LICENSE
codetective-0.1.0.dist-info/METADATA
codetective-0.1.0.dist-info/WHEEL
codetective-0.1.0.dist-info/entry_points.txt
codetective-0.1.0.dist-info/top_level.txt
codetective-0.1.0.dist-info/RECORD
