Metadata-Version: 2.4
Name: codetective
Version: 0.1.0
Summary: Multi-Agent Code Review Tool
Author-email: "Eng. Elias" <elias@engelias.website>
License: Copyright (c) 2025 Eng. Elias Owis
Project-URL: Homepage, https://github.com/Eng-Elias/codetective
Project-URL: Documentation, https://github.com/Eng-Elias/codetective/blob/main/README.md
Project-URL: Repository, https://github.com/Eng-Elias/codetective
Project-URL: Bug Tracker, https://github.com/Eng-Elias/codetective/issues
Keywords: code-review,security,static-analysis,ai,multi-agent
Classifier: Development Status :: 4 - Beta
Classifier: Intended Audience :: Developers
Classifier: Operating System :: OS Independent
Classifier: Programming Language :: Python :: 3
Classifier: Programming Language :: Python :: 3.10
Classifier: Programming Language :: Python :: 3.11
Classifier: Programming Language :: Python :: 3.12
Classifier: Topic :: Software Development :: Quality Assurance
Classifier: Topic :: Security
Classifier: Environment :: Console
Classifier: Environment :: Web Environment
Requires-Python: <3.13,>=3.10
License-File: LICENSE
Requires-Dist: click>=8.0.0
Requires-Dist: langgraph>=0.0.40
Requires-Dist: nicegui>=2.22.2
Requires-Dist: pydantic>=2.0.0
Requires-Dist: requests>=2.28.0
Requires-Dist: PyYAML>=6.0.0
Requires-Dist: rich>=13.0.0
Requires-Dist: typing-extensions>=4.0.0
Requires-Dist: ddgs>=4.0.0
Requires-Dist: langchain>=0.1.0
Requires-Dist: langchain-community>=0.0.10
Requires-Dist: langchain-ollama>=0.1.0
Requires-Dist: langgraph>=0.2.0
Requires-Dist: beautifulsoup4>=4.12.0
Provides-Extra: dev
Requires-Dist: pytest>=7.0.0; extra == "dev"
Requires-Dist: pytest-cov>=4.0.0; extra == "dev"
Requires-Dist: black>=22.0.0; extra == "dev"
Requires-Dist: isort>=5.0.0; extra == "dev"
Requires-Dist: flake8>=5.0.0; extra == "dev"
Requires-Dist: mypy>=1.0.0; extra == "dev"
Requires-Dist: types-requests>=2.32.4.20250809; extra == "dev"
Dynamic: license-file
